remi/__init__.py
remi/cli.py
remi/cli_utils.py
remi/file_transfer.py
remi/setup_commands.py
remi/user_interaction.py
remi/utils.py
remi/config/__init__.py
remi/config/defaults.py
remi/remote_compute/__init__.py
remi/remote_compute/cli_utils.py
remi/remote_compute/desktop.py
remi/remote_compute/singularity.py
remi/remote_compute/clusters/__init__.py
remi/remote_compute/clusters/cli_utils.py
remi/remote_compute/clusters/gricad.py
remi/remote_compute/clusters/inria_cluster.py
remi/remote_compute/clusters/oarsub.py
remi/remote_servers/__init__.py
remi/remote_servers/aim.py
remi/remote_servers/cli_utils.py
remi/remote_servers/jupyter.py
remi/remote_servers/remote_server.py
remi/remote_servers/tensorboard.py
remote_inria-1.7.4.dist-info/LICENSE
remote_inria-1.7.4.dist-info/METADATA
remote_inria-1.7.4.dist-info/WHEEL
remote_inria-1.7.4.dist-info/entry_points.txt
remote_inria-1.7.4.dist-info/top_level.txt
remote_inria-1.7.4.dist-info/RECORD
